{
    "basics": {
        "name": "Abhishek Sharma",
        "label": "Student",
        "picture": "",
        "email": "2021kuec2045@iiitkota.ac.in",
        "phone": "+918290673849",
        "website": "",
        "summary": "I'm a student of Indian Institute of Information technology,Kota (India), persuing my B.tech in Electronics and Communication engineering.",
        "location": {
            "address": "Kishangarh",
            "postalCode": "301405",
            "city": "Alwar",
            "countryCode": " India",
            "region": "Rajasthan"
        },
        "profiles": [
            {
                "network": "Twitter",
                "username": "",
                "url": ""
            },
            {
                "network": "Github",
                "username": "Abhishek003Sharma",
                "url": "https://github.com/Abhishek003Sharma"
            },
            {
                "network": "linkedin",
                "username": "",
                "url": ""
            },
            {
                "network": "Instagram",
                "username": "",
                "url": ""
            }
        ]
    },
    "work": [
        {
            "company": "",
            "position": "",
            "website": "",
            "startDate": "",
            "endDate": "",
            "summary": ""
        },
        {
            "company": "",
            "position": "",
            "website": "",
            "startDate": "",
            "endDate": "",
            "summary": ""
        },
        {
            "company": "",
            "position": "",
            "website": "",
            "startDate": "",
            "endDate": "",
            "summary": ""
        }
    ],
    "education": [
        {
            "institution": "Indian Institute of Information Technology,Kota",
            "area": "Engineering",
            "studyType": "Bachelor (hons)",
            "startDate": "",
            "endDate": "",
            "gpa": "",
            "courses": [
                "Electronics and Communication engineering"
            ]
        }
    ],
    "awards": [
        {
            "title": "",
            "awarder": "",
            "date": ""
        }
    ],
    "publications": [
        {
            "title": "",
            "details": "",
            "link": ""
        },
        {
            "title": "",
            "details": "",
            "link": ""
        },
        {
            "title": "",
            "details": "",
            "link": ""
        }
    ],
    "skills": [
        {
            "name": "",
            "level": "",
            "keywords": [
                "HTML",
                "CSS",
                "C/C++",
                "Python"
            ]
        }
    ],
    "languages": [
        {
            "language": "English",
            "fluency": "Native speaker"
        }
    ],
    "interests": [
        {
            "name": "Reading",
            "keywords": [
                "Books"
            ]
        },
        {
            "name": "Playing",
            "keywords": [
                "Badminton"
            ]
        }
    ]
}
